opentelemetry/util/evaluator/__init__.py
opentelemetry/util/evaluator/deepeval.py
opentelemetry/util/evaluator/deepeval_adapter.py
opentelemetry/util/evaluator/deepeval_metrics.py
opentelemetry/util/evaluator/deepeval_model.py
opentelemetry/util/evaluator/deepeval_runner.py
opentelemetry/util/evaluator/version.py
splunk_otel_genai_evals_deepeval-0.1.12.dist-info/METADATA
splunk_otel_genai_evals_deepeval-0.1.12.dist-info/WHEEL
splunk_otel_genai_evals_deepeval-0.1.12.dist-info/entry_points.txt
splunk_otel_genai_evals_deepeval-0.1.12.dist-info/licenses/LICENSE
splunk_otel_genai_evals_deepeval-0.1.12.dist-info/RECORD
