Metadata-Version: 2.4
Name: splunk-otel-genai-evals-deepeval
Version: 0.1.12
Summary: OpenTelemetry GenAI Utils
Project-URL: Homepage, https://github.com/open-telemetry/opentelemetry-python-contrib/tree/main/util/opentelemetry-util-genai
Project-URL: Repository, https://github.com/open-telemetry/opentelemetry-python-contrib
Author-email: OpenTelemetry Authors <cncf-opentelemetry-contributors@lists.cncf.io>
License-Expression: Apache-2.0
License-File: LICENSE
Classifier: Development Status :: 4 - Beta
Classifier: Intended Audience :: Developers
Classifier: License :: OSI Approved :: Apache Software License
Classifier: Programming Language :: Python
Classifier: Programming Language :: Python :: 3
Classifier: Programming Language :: Python :: 3.9
Classifier: Programming Language :: Python :: 3.10
Classifier: Programming Language :: Python :: 3.11
Classifier: Programming Language :: Python :: 3.12
Classifier: Programming Language :: Python :: 3.13
Requires-Python: >=3.9
Requires-Dist: deepeval<3.8.0,>=3.3.9
Requires-Dist: openai>=1.0.0
Requires-Dist: splunk-otel-util-genai-evals>=0.1.4
Requires-Dist: splunk-otel-util-genai>=0.1.4
Provides-Extra: fsspec
Requires-Dist: fsspec>=2025.9.0; extra == 'fsspec'
Provides-Extra: test
Requires-Dist: pytest>=7.0.0; extra == 'test'
